pytu/__init__.py
pytu/matt.py
pytu/tools.py
pytu-0.1.5.dist-info/WHEEL
pytu-0.1.5.dist-info/METADATA
pytu-0.1.5.dist-info/RECORD
