Metadata-Version: 2.1
Name: pytu
Version: 0.1.5
Summary: My personal Python Tuuls :-)
Author: Michal Mikolas
Author-email: nanuqcz@gmail.com
Requires-Python: >=3.7,<4.0
Classifier: Programming Language :: Python :: 3
Classifier: Programming Language :: Python :: 3.10
Classifier: Programming Language :: Python :: 3.7
Classifier: Programming Language :: Python :: 3.8
Classifier: Programming Language :: Python :: 3.9
